controllers/__init__.py
controllers/abstractcontroller.py
controllers/amptek_controller.py
controllers/csu_rx_controller.py
controllers/lasercontroller.py
controllers/nanomax_controller.py
controllers/nanomax_scan_cube.py
controllers/test_nanomax.py
controllers/zaber_controller.py
controllers/bin/BBD_Stages.xml
controllers/bin/ThorLabs.MotionControl.Benchtop.DCServoCLI.dll
controllers/bin/ThorLabs.MotionControl.Benchtop.PrecisionPiezoCLI.dll
controllers/bin/ThorLabs.MotionControl.FilterFlipper.h
controllers/bin/ThorLabs.MotionControl.KCube.DCServoCLI.dll
controllers/bin/ThorLabs.MotionControl.KCube.LaserDiodeCLI.dll
controllers/bin/ThorLabs.MotionControl.KCube.LaserSourceCLI.dll
controllers/bin/ThorLabs.MotionControl.KCube.PositionAlignerCLI.dll
controllers/bin/ThorLabs.MotionControl.KCube.StrainGaugeCLI.dll
controllers/bin/ThorLabs.MotionControl.ModularRack.h
controllers/bin/ThorLabs.MotionControl.PolarizerCLI.dll
controllers/bin/ThorLabs.MotionControl.TCube.InertialMotorCLI.dll
controllers/bin/ThorLabs.MotionControl.TDIEngineCLI.dll
controllers/bin/ThorLabs.MotionControl.VerticalStageCLI.dll
controllers/bin/Thorlabs.APT.dll
controllers/bin/Thorlabs.MotionControl.Benchtop.BrushlessMotor.dll
controllers/bin/Thorlabs.MotionControl.Benchtop.BrushlessMotor.h
controllers/bin/Thorlabs.MotionControl.Benchtop.BrushlessMotor.lib
controllers/bin/Thorlabs.MotionControl.Benchtop.BrushlessMotorCLI.dll
controllers/bin/Thorlabs.MotionControl.Benchtop.BrushlessMotorUI.dll
controllers/bin/Thorlabs.MotionControl.Benchtop.DCServo.dll
controllers/bin/Thorlabs.MotionControl.Benchtop.DCServo.h
controllers/bin/Thorlabs.MotionControl.Benchtop.DCServo.lib
controllers/bin/Thorlabs.MotionControl.Benchtop.DCServoUI.dll
controllers/bin/Thorlabs.MotionControl.Benchtop.NanoTrak.dll
controllers/bin/Thorlabs.MotionControl.Benchtop.NanoTrak.h
controllers/bin/Thorlabs.MotionControl.Benchtop.NanoTrak.lib
controllers/bin/Thorlabs.MotionControl.Benchtop.NanoTrakCLI.dll
loucomax_controllers-1.0.3.dist-info/licenses/LICENSE
loucomax_controllers-1.0.3.dist-info/METADATA
loucomax_controllers-1.0.3.dist-info/WHEEL
loucomax_controllers-1.0.3.dist-info/top_level.txt
loucomax_controllers-1.0.3.dist-info/RECORD
