Metadata-Version: 2.4
Name: loucomax_controllers
Version: 1.0.3
Summary: Controllers for all devices used in the LouCOMAX (CNRS) project
Author: BLASIAK Antoine
Author-email: antoineblasiak66@gmail.com
Classifier: Programming Language :: Python :: 3
Classifier: Operating System :: OS Independent
Classifier: License :: OSI Approved :: MIT License
Requires-Python: >=3.8
License-File: LICENSE
Requires-Dist: numpy
Requires-Dist: overrides
Requires-Dist: pythonnet
Requires-Dist: h5py
Requires-Dist: matplotlib
Requires-Dist: configparser
Requires-Dist: pyusb
Requires-Dist: pyserial
Requires-Dist: PyQt5
Requires-Dist: csu2controller
Requires-Dist: zaber_motion
Dynamic: author
Dynamic: author-email
Dynamic: classifier
Dynamic: description
Dynamic: description-content-type
Dynamic: license-file
Dynamic: requires-dist
Dynamic: requires-python
Dynamic: summary
